jinsi/__init__.py
jinsi/__main__.py
jinsi/__pkginfo__.py
jinsi/api.py
jinsi/environment.py
jinsi/exceptions.py
jinsi/expressions.py
jinsi/functions.py
jinsi/jsonutil.py
jinsi/main.py
jinsi/nodes.py
jinsi/parser.py
jinsi/util.py
jinsi/value.py
jinsi/yamlutil.py
jinsi-0.19.1.data/scripts/jinsi
tests/__init__.py
tests/common.py
tests/test_conditionals.py
tests/test_dates.py
tests/test_each.py
tests/test_examples.py
tests/test_functions.py
tests/test_functions_integrated.py
tests/test_jsonutil.py
tests/test_load.py
tests/test_main.py
tests/test_yamlutil.py
jinsi-0.19.1.dist-info/LICENSE
jinsi-0.19.1.dist-info/METADATA
jinsi-0.19.1.dist-info/WHEEL
jinsi-0.19.1.dist-info/top_level.txt
jinsi-0.19.1.dist-info/RECORD
