Metadata-Version: 2.1
Name: jinsi
Version: 0.19.1
Summary: JSON/YAML homoiconic templating language
Home-page: https://github.com/scravy/jinsi
Author: Julian Fleischer
Author-email: tirednesscankill@warhog.net
Classifier: Programming Language :: Python :: 3
Classifier: License :: OSI Approved :: MIT License
Classifier: Operating System :: OS Independent
Requires-Python: >=3.7
License-File: LICENSE
Requires-Dist: awesome-pattern-matching (>=0.20.1)
Requires-Dist: pyyaml (>=5.0.0)
